{"State.bc209c48-6675-4c3d-91c8-da69ed9eef38": {"id": "bc209c48-6675-4c3d-91c8-da69ed9eef38", "updated_at": "2023-08-23T17:52:32.947265", "name": "California", "__class__": "State", "created_at": "2023-08-23T17:52:32.947250"}, "State.458688b1-faf3-4cf3-af56-134939882294": {"id": "458688b1-faf3-4cf3-af56-134939882294", "updated_at": "2023-08-23T17:52:32.947731", "name": "Arizona", "__class__": "State", "created_at": "2023-08-23T17:52:32.947716"}, "Place.053626f7-88e8-4fb9-b4d4-95a1f41ba9eb": {"latitude": 37.773972, "city_id": "0001", "id": "053626f7-88e8-4fb9-b4d4-95a1f41ba9eb", "updated_at": "2023-08-23T19:03:02.945512", "longitude": -122.431297, "price_by_night": 300, "number_bathrooms": 2, "created_at": "2023-08-23T19:03:02.945497", "max_guest": 10, "number_rooms": 4, "name": "My little house", "__class__": "Place", "user_id": "0001"}, "State.7c1d5600-1546-481d-9e8c-f8623175a230": {"id": "7c1d5600-1546-481d-9e8c-f8623175a230", "updated_at": "2023-08-23T19:21:11.845479", "name": "Arizona", "__class__": "State", "created_at": "2023-08-23T19:21:11.845463"}, "State.2451a52d-7cab-4398-8a9a-157c8afcc740": {"id": "2451a52d-7cab-4398-8a9a-157c8afcc740", "updated_at": "2023-08-23T19:03:02.944158", "name": "Arizona", "__class__": "State", "created_at": "2023-08-23T19:03:02.944146"}, "Place.0e7b376e-2103-4ebe-9c99-940fbabf94ee": {"latitude": 37.773972, "city_id": "0001", "id": "0e7b376e-2103-4ebe-9c99-940fbabf94ee", "updated_at": "2023-08-23T19:21:11.846879", "longitude": -122.431297, "price_by_night": 300, "number_bathrooms": 2, "created_at": "2023-08-23T19:21:11.846864", "max_guest": 10, "number_rooms": 4, "name": "My little house", "__class__": "Place", "user_id": "0001"}, "Place.d14c94e3-6361-4e67-8c5e-bea03064258a": {"latitude": 37.773972, "city_id": "0001", "id": "d14c94e3-6361-4e67-8c5e-bea03064258a", "updated_at": "2023-08-23T17:52:32.948886", "longitude": -122.431297, "price_by_night": 300, "number_bathrooms": 2, "created_at": "2023-08-23T17:52:32.948867", "max_guest": 10, "number_rooms": 4, "name": "My little house", "__class__": "Place", "user_id": "0001"}}